geo_chile/__init__.py
geo_chile/admin.py
geo_chile/apps.py
geo_chile/management/__init__.py
geo_chile/management/commands/__init__.py
geo_chile/management/commands/load_geo_chile_data.py
geo_chile/migrations/0001_initial.py
geo_chile/migrations/0002_auto_20200619_1717.py
geo_chile/migrations/__init__.py
geo_chile/models.py
django_geo_chile-1.0.2.dist-info/WHEEL
django_geo_chile-1.0.2.dist-info/METADATA
django_geo_chile-1.0.2.dist-info/RECORD
