Metadata-Version: 2.1
Name: django-geo-chile
Version: 1.0.2
Summary: Models and management command to load Chile's Administrative Geographical data from official source.
Home-page: https://github.com/fceruti/django-geo-chile
License: MIT
Author: Francisco Ceruti
Author-email: hello@fceruti.com
Maintainer: Francisco Ceruti
Maintainer-email: hello@fceruti.com
Requires-Python: >=3.6,<4.0
Classifier: License :: OSI Approved :: MIT License
Classifier: Programming Language :: Python :: 3
Classifier: Programming Language :: Python :: 3.6
Classifier: Programming Language :: Python :: 3.7
Classifier: Programming Language :: Python :: 3.8
Requires-Dist: django (>=2.2)
Requires-Dist: requests (>=2.23.0,<3.0.0)
Project-URL: Repository, https://github.com/fceruti/django-geo-chile
